NSlogger/__init__.py
NSlogger-1.0.0.dist-info/LICENSE
NSlogger-1.0.0.dist-info/METADATA
NSlogger-1.0.0.dist-info/WHEEL
NSlogger-1.0.0.dist-info/top_level.txt
NSlogger-1.0.0.dist-info/RECORD
